README.md
setup.cfg
setup.py
media_preprocessor/__init__.py
media_preprocessor/media_preprocessor.py
media_preprocessor.egg-info/PKG-INFO
media_preprocessor.egg-info/SOURCES.txt
media_preprocessor.egg-info/dependency_links.txt
media_preprocessor.egg-info/requires.txt
media_preprocessor.egg-info/top_level.txt