Metadata-Version: 2.1
Name: media-preprocessor
Version: 10.0
Summary: tool for preprocessing media
Home-page: https://github.com/harshh-mahajan/media_preprocessor
Author: Harsh Mahajan, Akash Patil, Pranit Shriyan, Jayesh Singh, Shankh Suri, Tazeem Khan
Author-email: harsh.mahajan28@nmims.edu.in
License: MIT
Download-URL: https://github.com/harshh-mahajan/media_preprocessor/archive/10.0.tar.gz
Keywords: image,preprocessing,reshape,resize,background
Platform: UNKNOWN
Classifier: Development Status :: 3 - Alpha
Classifier: Intended Audience :: Developers
Classifier: Topic :: Software Development :: Build Tools
Classifier: License :: OSI Approved :: MIT License
Classifier: Programming Language :: Python :: 3
Classifier: Programming Language :: Python :: 3.4
Classifier: Programming Language :: Python :: 3.5
Classifier: Programming Language :: Python :: 3.6
